{
    "id": "5c6a00483e1e1e27a8cf35a1",
    "name": "oauth2-google",
    "type": "oauth2-google",
    "config": {
        "clientId": "238095324198-q1vvoh5nrcortevgt7k90gbmd8gqmop4.apps.googleusercontent.com"
    },
    "secret_config": {
        "clientSecret": "__oauth2-google_clientSecret"
    },
    "disabled": false,
    "metadata_fields": [
        {
            "required": false,
            "name": "first_name"
        },
        {
            "required": false,
            "name": "last_name"
        },
        {
            "required": false,
            "name": "email"
        }
    ],
    "redirect_uris": [
        "https://diary.bkman.rocks/",
        "http://localhost:8080/"
    ]
}
